__init__.py
enums.py
lists.py
media.py
texts.py
urls.py
wolne_lektury-0.1.0.dist-info/METADATA
wolne_lektury-0.1.0.dist-info/WHEEL
wolne_lektury-0.1.0.dist-info/top_level.txt
wolne_lektury-0.1.0.dist-info/RECORD
