Metadata-Version: 2.1
Name: wolne-lektury
Version: 0.1.0
Summary: Playing with embedding vectors
Home-page: https://github.com/krzjoa/wolne_lektury
Author: Krzysztof Joachimiak
Author-email: joachimiak.krzysztof@gmail.com
Project-URL: Bug Tracker, https://github.com/krzjoa/wolne_lektury/issues
Classifier: Programming Language :: Python :: 3
Classifier: License :: OSI Approved :: MIT License
Classifier: Operating System :: OS Independent
Requires-Python: >=3.6
